unicex/__init__.py
unicex/enums.py
unicex/exceptions.py
unicex/extra.py
unicex/mapper.py
unicex/types.py
unicex/utils.py
unicex/_abc/__init__.py
unicex/_abc/exchange_info.py
unicex/_abc/uni_client.py
unicex/_abc/uni_websocket_manager.py
unicex/_base/__init__.py
unicex/_base/client.py
unicex/_base/websocket.py
unicex/aster/__init__.py
unicex/aster/adapter.py
unicex/aster/client.py
unicex/aster/exchange_info.py
unicex/aster/uni_client.py
unicex/aster/uni_websocket_manager.py
unicex/aster/user_websocket.py
unicex/aster/websocket_manager.py
unicex/binance/__init__.py
unicex/binance/adapter.py
unicex/binance/client.py
unicex/binance/exchange_info.py
unicex/binance/uni_client.py
unicex/binance/uni_websocket_manager.py
unicex/binance/user_websocket.py
unicex/binance/websocket_manager.py
unicex/bingx/__init__.py
unicex/bingx/adapter.py
unicex/bingx/client.py
unicex/bingx/exchange_info.py
unicex/bingx/uni_client.py
unicex/bingx/uni_websocket_manager.py
unicex/bingx/user_websocket.py
unicex/bingx/websocket_manager.py
unicex/bitget/__init__.py
unicex/bitget/adapter.py
unicex/bitget/client.py
unicex/bitget/exchange_info.py
unicex/bitget/uni_client.py
unicex/bitget/uni_websocket_manager.py
unicex/bitget/user_websocket.py
unicex/bitget/websocket_manager.py
unicex/bybit/__init__.py
unicex/bybit/adapter.py
unicex/bybit/client.py
unicex/bybit/exchange_info.py
unicex/bybit/uni_client.py
unicex/bybit/uni_websocket_manager.py
unicex/bybit/user_websocket.py
unicex/bybit/websocket_manager.py
unicex/gate/__init__.py
unicex/gate/adapter.py
unicex/gate/client.py
unicex/gate/exchange_info.py
unicex/gate/uni_client.py
unicex/gate/uni_websocket_manager.py
unicex/gate/user_websocket.py
unicex/gate/websocket_manager.py
unicex/hyperliquid/__init__.py
unicex/hyperliquid/adapter.py
unicex/hyperliquid/client.py
unicex/hyperliquid/exchange_info.py
unicex/hyperliquid/uni_client.py
unicex/hyperliquid/uni_websocket_manager.py
unicex/hyperliquid/user_websocket.py
unicex/hyperliquid/websocket_manager.py
unicex-0.17.9.dist-info/licenses/LICENSE
unicex-0.17.9.dist-info/METADATA
unicex-0.17.9.dist-info/WHEEL
unicex-0.17.9.dist-info/top_level.txt
unicex-0.17.9.dist-info/RECORD
