Metadata-Version: 2.4
Name: unicex
Version: 0.17.9
Summary: Unified Crypto Exchange API 
Author-email: LoveBloodAndDiamonds <ayazshakirzyanov27@gmail.com>
License: BSD 3-Clause License
Project-URL: Github, https://github.com/LoveBloodAndDiamonds/uni-cex-api
Project-URL: Author, https://t.me/LoveBloodAndDiamonds
Project-URL: Readthedocs, https://unicex.readthedocs.io/ru/latest/
Requires-Python: >=3.12
License-File: LICENSE
Requires-Dist: aiohttp>=3.12.15
Requires-Dist: eth-account>=0.13.7
Requires-Dist: loguru>=0.7.3
Requires-Dist: msgpack>=1.1.1
Requires-Dist: orjson>=3.11.3
Requires-Dist: protobuf>=6.32.1
Requires-Dist: websockets>=15.0.1
Dynamic: license-file
